{
  "$schema": "https://mintlify.com/docs.json",
  "theme": "mint",
  "name": "RPC by Gateway.fm Docs",
  "colors": {
    "primary": "#8950fa",
    "light": "#8950fa",
    "dark": "#8950fa"
  },
  "favicon": "/logo/logo.svg",
  "navigation": {
    "groups": [
      {
        "group": "Overview",
        "pages": [
          "docs/intro",
          "docs/supported-networks",
          "docs/endpoints",
          "docs/support"
        ]
      },
      {
        "group": "Guides",
        "pages": [
          "docs/get-api-key",
          "docs/ethersjs-rpc-call",
          "docs/web3py-rpc-call"
        ]
      },
      {
        "group": "API Reference", 
        "pages": [
          "docs/api-intro",
          "api/playground"
        ]
      }
    ]
  },
  "logo": {
    "light": "/logo/logo.png",
    "dark": "/logo/logo.png",
    "href": "https://gateway.fm/rpc/"
  },
  "footer": {
    "socials": {
      "x": "https://x.com/gateway_eth",
      "github": "https://github.com/gateway-fm",
      "linkedin": "https://www.linkedin.com/company/gateway-fm/posts/?feedView=all"
    }
  }
}
